dictbelt/__init__.py
dictbelt/functional.py
dictbelt/wrapper.py
dictbelt-1.0.2.dist-info/WHEEL
dictbelt-1.0.2.dist-info/METADATA
dictbelt-1.0.2.dist-info/RECORD
